yuntu/__init__.py
yuntu/collection/__init__.py
yuntu/collection/base.py
yuntu/collection/methods.py
yuntu/collection/server.py
yuntu/collection/utils.py
yuntu/core/__init__.py
yuntu/core/audio/__init__.py
yuntu/core/audio/base.py
yuntu/core/audio/methods.py
yuntu/core/audio/utils.py
yuntu/core/common/__init__.py
yuntu/core/common/utils.py
yuntu/core/datastore/__init__.py
yuntu/core/datastore/base.py
yuntu/core/datastore/methods.py
yuntu/core/datastore/utils.py
yuntu/core/db/__init__.py
yuntu/core/db/base.py
yuntu/core/db/methods.py
yuntu/core/db/utils.py
yuntu/dataset/__init__.py
yuntu/dataset/base.py
yuntu/dataset/methods.py
yuntu/soundscape/__init__.py
yuntu/soundscape/analysis.py
yuntu/soundscape/base.py
yuntu/soundscape/methods.py
yuntu/soundscape/ops.py
yuntu/soundscape/utils.py
yuntu/soundscape/views.py
yuntu-0.1.1.dist-info/LICENCE.txt
yuntu-0.1.1.dist-info/METADATA
yuntu-0.1.1.dist-info/WHEEL
yuntu-0.1.1.dist-info/top_level.txt
yuntu-0.1.1.dist-info/RECORD
